src/__init__.py
src/cache.py
src/constants.py
src/mcp_server.py
src/parser.py
src/scraper.py
src/transformer.py
timedoctor_mcp-1.3.0.dist-info/METADATA
timedoctor_mcp-1.3.0.dist-info/WHEEL
timedoctor_mcp-1.3.0.dist-info/entry_points.txt
timedoctor_mcp-1.3.0.dist-info/licenses/LICENSE
timedoctor_mcp-1.3.0.dist-info/RECORD
