Metadata-Version: 2.4
Name: timedoctor-mcp
Version: 1.3.0
Summary: MCP Server for extracting Time Doctor time tracking data via AI assistants
Project-URL: Homepage, https://github.com/frifster/timedoctor-mcp
Project-URL: Repository, https://github.com/frifster/timedoctor-mcp
Project-URL: Issues, https://github.com/frifster/timedoctor-mcp/issues
Project-URL: Funding, https://buymeacoffee.com/frifster
Author-email: frifster <frifster2014@gmail.com>
License: MIT
License-File: LICENSE
Keywords: ai,claude,cursor,gemini,mcp,time-doctor,time-tracking
Classifier: Development Status :: 5 - Production/Stable
Classifier: Intended Audience :: Developers
Classifier: License :: OSI Approved :: MIT License
Classifier: Programming Language :: Python :: 3
Classifier: Programming Language :: Python :: 3.12
Classifier: Programming Language :: Python :: 3.13
Requires-Python: >=3.12
Requires-Dist: beautifulsoup4>=4.12.3
Requires-Dist: colorlog>=6.9.0
Requires-Dist: lxml>=5.3.0
Requires-Dist: mcp>=1.1.2
Requires-Dist: playwright>=1.48.0
Requires-Dist: python-dateutil>=2.9.0
Requires-Dist: python-dotenv>=1.0.1
Requires-Dist: requests>=2.32.3
Requires-Dist: tenacity>=8.2.0
Provides-Extra: dev
Requires-Dist: ruff>=0.8.4; extra == 'dev'
